<?xml version="1.0"?>

<device>
    <make>Sony</make>
    <model>PSP</model>
    <description>H.264/AAC for Playstation portable</description>
    <author>
        <name>Daniel G. Taylor</name>
        <email>dan@programmer-art.org</email>
    </author>
    <version>1.0</version>
    <icon>file://psp.svg</icon>
    <default>Normal</default>
    
    <profile>
        <name>Low</name>
        <container>video/quicktime,variant=iso</container>
        <extension>mp4</extension>
        <audio>
            <name>audio/mpeg,mpegversion=4</name>
            <presets>
                <preset>Quality Low, Profile Low Complexity</preset>
            </presets>
            <samplerate>48000</samplerate>
            <channels>1, 2</channels>
        </audio>
        <video>
            <name>video/x-h264</name>
            <border>N</border>
            <passes>0</passes>
            <pixelaspectratio>0/0</pixelaspectratio>
            <presets>
                <preset>Quality Low, Profile Baseline</preset>
            </presets> 
            <width>320</width>
            <height>240</height>
            <framerate>1, 25</framerate>
        </video>
    </profile>
    <profile>
        <name>Normal</name>
        <container>video/quicktime,variant=iso</container>
        <extension>mp4</extension>
        <audio>
            <name>audio/mpeg,mpegversion=4</name>
            <presets>
                <preset>Quality Normal,Profile Low Complexity</preset>
            </presets>
            <samplerate>48000</samplerate>
            <channels>1, 2</channels>
        </audio>
        <video>
            <name>video/x-h264</name>
            <border>N</border>
            <passes>0</passes>
            <pixelaspectratio>0/0</pixelaspectratio>
            <presets>
                <preset>Quality Normal, Profile Main</preset>
            </presets>
            <width>320	</width>
            <height>240</height>
            <framerate>1, 25</framerate>
        </video>
    </profile>
</device>

